setup.py
cutImages/__init__.py
cutImages.egg-info/PKG-INFO
cutImages.egg-info/SOURCES.txt
cutImages.egg-info/dependency_links.txt
cutImages.egg-info/requires.txt
cutImages.egg-info/top_level.txt