Metadata-Version: 1.0
Name: cutImages
Version: 0.61
Summary: Automatic batch cutting by lshxiao
Home-page: http://py.pxuexiao.com/cutImages
Author: lshxiao
Author-email: lshxiao@163.com
License: http://www.apache.org/licenses/LICENSE-2.0.html
Platform: any
